{"frames":{"rdm":{"axisR":{"valence":0.902,"power":0.3,"arousal":0.38,"novelty":0.747},"unique":{"valence":0.143,"power":0.005,"arousal":0.058,"novelty":0.029}},"gpa":{"phi":{"valence":0.846,"power":0.745,"arousal":0.68,"novelty":0.68},"unique":{"valence":0.477,"power":0.147,"arousal":0.116,"novelty":0.306}}},"resolution":{"levels":{"valence":{"knn":0.879,"olsOof":0.893,"axis":0.902},"power":{"knn":0.699,"olsOof":0.736,"axis":0.3},"arousal":{"knn":0.477,"olsOof":0.653,"axis":0.38},"novelty":{"knn":0.556,"olsOof":0.573,"axis":0.747}},"gridSelfAxis":{"valence":0.9,"power":0.292,"arousal":0.682,"novelty":0.601},"heldout":{"rdm":0.747,"gpa":0.748,"null95":0.145,"powerRdm":0.846,"powerGpa":0.904}},"null95MinAxisR":0.135,"crossLanguage":[{"language":"english","nTerms":77,"rsaGrid":0.463,"meanAxisR":0.582,"knnR2":{"valence":0.879,"power":0.699,"arousal":0.477,"novelty":0.556}},{"language":"french","nTerms":49,"rsaGrid":0.54,"meanAxisR":0.547,"knnR2":{"valence":0.844,"power":0.583,"arousal":0.542,"novelty":0.535}},{"language":"indonesian","nTerms":40,"rsaGrid":0.362,"meanAxisR":0.51,"knnR2":{"valence":0.735,"power":0.361,"arousal":0.196,"novelty":0.125}}]}